Metadata-Version: 2.1
Name: honeypotsjkdb
Version: 0.1
Summary: 30 different honeypots in one package! (dhcp, dns, elastic, ftp, http proxy, https proxy, http, https, imap, ipp, irc, ldap, memcache, mssql, mysql, ntp, oracle, pjl, pop3, postgres, rdp, redis, sip, smb, smtp, snmp, socks5, ssh, telnet, vnc)
Home-page: https://github.com/qeeqbox/honeypots
License: AGPL-3.0
Platform: UNKNOWN
Requires-Python: >=3.5
Requires-Dist: impacket (==0.9.24)
Requires-Dist: netifaces (==0.11.0)
Requires-Dist: paramiko (==3.1.0)
Requires-Dist: psutil (==5.9.0)
Requires-Dist: psycopg2-binary (==2.9.3)
Requires-Dist: pycrypto (==2.6.1)
Requires-Dist: requests (==2.28.2)
Requires-Dist: requests[socks] (==2.28.2)
Requires-Dist: scapy (==2.4.5)
Requires-Dist: service-identity (==21.1.0)
Requires-Dist: twisted (==21.7.0)
Provides-Extra: test
Requires-Dist: elasticsearch ; extra == 'test'
Requires-Dist: ldap3 ; extra == 'test'
Requires-Dist: mysql-connector ; extra == 'test'
Requires-Dist: pymssql ; extra == 'test'
Requires-Dist: pysnmp ; extra == 'test'
Requires-Dist: redis ; extra == 'test'
